Topsis/__init__.py
Topsis/__main__.py
Topsis_Samarjot_102003242-1.0.dist-info/Licence.txt
Topsis_Samarjot_102003242-1.0.dist-info/METADATA
Topsis_Samarjot_102003242-1.0.dist-info/WHEEL
Topsis_Samarjot_102003242-1.0.dist-info/entry_points.txt
Topsis_Samarjot_102003242-1.0.dist-info/top_level.txt
Topsis_Samarjot_102003242-1.0.dist-info/RECORD
