Metadata-Version: 2.1
Name: Topsis-Samarjot-102003242
Version: 1.0
Summary: Python package implementing TOPSIS multi-criteria decision making method.
Author: Samarjot Singh
Author-email: 2001samar@gmail.com
License: MIT
Classifier: License :: OSI Approved :: MIT License
Classifier: Programming Language :: Python :: 3
Classifier: Programming Language :: Python :: 3.11
License-File: Licence.txt
Requires-Dist: numpy
Requires-Dist: pandas
